<?xml version="1.0" encoding="UTF-8"?>
<objects serializationModel="Studio.01.08.00">
    <object class="AudioFile" id="{3bcc253c-a99a-454d-8c45-2a8a664863e5}">
        <property name="assetPath">
            <value>TONALFma2.wav</value>
        </property>
        <property name="frequencyInKHz">
            <value>44.0999985</value>
        </property>
        <property name="channelCount">
            <value>2</value>
        </property>
        <property name="length">
            <value>8</value>
        </property>
        <relationship name="masterAssetFolder">
            <destination>{99bd6b42-d381-40af-a07f-80ea3f21c3c4}</destination>
        </relationship>
    </object>
</objects>
